{
  "batch": 5,
  "questions": [
    {
      "id": 41,
      "type": "single_choice",
      "question": "Solution: Use notebookutils.credentials.getSecret and specify the key vault URL and the name of a linked service. Does this meet the goal?",
      "options": {
        "A": "Yes",
        "B": "No"
      },
      "answer": ["B"]
    },
    {
      "id": 42,
      "type": "drag_drop",
      "question": "You have two Fabric notebooks named Load_Salesperson and Load_Orders that read data from Parquet files and write to Delta tables. Load_Orders depends on the successful execution of Load_Salesperson. You need to dynamically execute the notebooks in the correct order using a notebook DAG.",
      "answers": {
        "DAGCollection": "activities",
        "DependencyProperty": "dependencies",
        "ExecutionMethod": "runMultiple"
      }
    },
    {
      "id": 43,
      "type": "dropdown",
      "question": "You are building a data pipeline named Dynamic Data Copy. The pipeline must receive a list of tables to copy using a ForEach activity. Complete the pipeline expression.",
      "answers": {
        "ActivityName": "Lookup Schema and Table",
        "OutputProperty": "output.value"
      }
    },
    {
      "id": 44,
      "type": "dropdown",
      "question": "You must configure dynamic data masking in a Fabric warehouse so that BirthDate displays 1900-01-01 and EmailAddress only shows the first and last characters.",
      "answers": {
        "BirthDateMask": "random(1900-01-01, 1900-01-01)",
        "EmailMask": "partial(1,\"@\",5)"
      }
    },
    {
      "id": 45,
      "type": "single_choice",
      "question": "You have a Fabric workspace containing Report1, Dashboard1, Model1 and Lakehouse1. Which items can be endorsed in Fabric?",
      "options": {
        "A": "Lakehouse1, Model1 and Dashboard1 only",
        "B": "Lakehouse1, Model1, Report1 and Dashboard1",
        "C": "Report1 and Dashboard1 only",
        "D": "Model1, Report1 and Dashboard1 only",
        "E": "Lakehouse1, Model1 and Report1 only"
      },
      "answer": ["E"]
    },
    {
      "id": 46,
      "type": "single_choice",
      "question": "You configure source control for a Fabric workspace using GitHub. Which permissions are required to commit code while following least privilege?",
      "options": {
        "A": "Actions (Read and write) and Contents (Read and write)",
        "B": "Actions (Read and write) only",
        "C": "Contents (Read and write) only",
        "D": "Contents (Read) and Commit statuses (Read and write)"
      },
      "answer": ["C"]
    },
    {
      "id": 47,
      "type": "single_choice",
      "question": "You configure Git integration for a Fabric workspace using an Azure DevOps Git repository. Which details are required for the integration?",
      "options": {
        "A": "Organization, project, repository, and branch",
        "B": "PAT token and repository URL",
        "C": "Project, repository, branch, and folder",
        "D": "Repository URL and folder"
      },
      "answer": ["A"]
    },
    {
      "id": 48,
      "type": "multi_select",
      "question": "You must run a notebook daily at 07:00 UTC, retry twice if it fails, and refresh a semantic model after the notebook completes successfully. Which three actions should you perform?",
      "options": {
        "A": "Link refresh activity using On success",
        "B": "Set pipeline schedule timezone to UTC",
        "C": "Set Notebook retry to 2",
        "D": "Set notebook schedule timezone to UTC",
        "E": "Set refresh activity retry to 2",
        "F": "Link refresh using On completion"
      },
      "answer": ["A", "B", "C"]
    },
    {
      "id": 49,
      "type": "single_choice",
      "question": "You pass an integer parameter param1 into a Fabric data pipeline. How should you reference the parameter so it returns an integer value?",
      "options": {
        "A": "@pipeline().parameters.param1",
        "B": "@{pipeline().parameters.param1}",
        "C": "@(pipeline().parameters.[param1])",
        "D": "@@{pipeline().parameters.param1}"
      },
      "answer": ["A"]
    },
    {
      "id": 50,
      "type": "single_choice",
      "question": "You must orchestrate a Dataflow Gen2, a notebook transformation, and a CSV ingestion so that they run sequentially every 15 minutes. Which Fabric item should you use?",
      "options": {
        "A": "Notebook",
        "B": "Warehouse",
        "C": "Dataflow Gen2",
        "D": "Data pipeline"
      },
      "answer": ["D"]
    }
  ]
}
